aiopyo365/__init__.py
aiopyo365/config.py
aiopyo365/exceptions.py
aiopyo365/factories/abstract.py
aiopyo365/factories/drive_items.py
aiopyo365/factories/sites.py
aiopyo365/providers/auth.py
aiopyo365/ressources/files.py
aiopyo365/ressources/sites.py
aiopyo365/services/sharepoint.py
aiopyo365-0.1.1a0.dist-info/WHEEL
aiopyo365-0.1.1a0.dist-info/METADATA
aiopyo365-0.1.1a0.dist-info/RECORD
