Metadata-Version: 2.1
Name: aiopyo365
Version: 0.1.1a0
Summary: 
Author: gonza
Author-email: matgonzalez@hotmail.fr
Requires-Python: >=3.8.1,<4.0
Classifier: Programming Language :: Python :: 3
Classifier: Programming Language :: Python :: 3.9
Classifier: Programming Language :: Python :: 3.10
Classifier: Programming Language :: Python :: 3.11
Requires-Dist: aiohttp (>=3.8.3,<4.0.0)
